{"is_source_file": true, "format": "CSS", "description": "Stylesheet defining CSS variables for colors, typography, spacing, shadows, and utility classes for a frontend project.", "external_files": [], "external_methods": [], "published": [], "classes": [], "methods": [], "calls": [], "search-terms": ["color-ffffff", "font-lobster", "bg-dark", "typo-hero"], "state": 2, "file_id": 7, "knowledge_revision": 15, "git_revision": "", "hash": "cedd8f516edbdfeb56f7f7d6ac71f0b9", "format-version": 4, "code-base-name": "tic_tac_toe_frontend", "filename": "tic_tac_toe_frontend/src/styles/common.css", "revision_history": [{"15": ""}]}